target_jsonl.py
target_jsonl-0.1.4.dist-info/LICENSE
target_jsonl-0.1.4.dist-info/METADATA
target_jsonl-0.1.4.dist-info/WHEEL
target_jsonl-0.1.4.dist-info/entry_points.txt
target_jsonl-0.1.4.dist-info/top_level.txt
target_jsonl-0.1.4.dist-info/RECORD
