Metadata-Version: 2.1
Name: target-jsonl
Version: 0.1.4
Summary: Singer.io target for writing JSON Line files
Home-page: https://github.com/andyh1203/target-jsonl
Author: Andy Huynh
Author-email: andy.huynh312@gmail.com
License: UNKNOWN
Keywords: singer,singer.io,target,etl
Platform: UNKNOWN
Classifier: Programming Language :: Python :: 3 :: Only
Requires-Dist: jsonschema (==2.6.0)
Requires-Dist: singer-python (==5.8.0)
Requires-Dist: adjust-precision-for-schema (==0.3.3)
